infervcpy/__init__.py
infervcpy/main.py
infervcpy/root_pipe.py
infervcpy/lib/__init__.py
infervcpy/lib/audio.py
infervcpy/lib/log_config.py
infervcpy/lib/rmvpe.py
infervcpy/lib/infer_pack/__init__.py
infervcpy/lib/infer_pack/attentions.py
infervcpy/lib/infer_pack/commons.py
infervcpy/lib/infer_pack/models.py
infervcpy/lib/infer_pack/modules.py
infervcpy/lib/infer_pack/transforms.py
infervcpy-1.6.dist-info/LICENSE
infervcpy-1.6.dist-info/METADATA
infervcpy-1.6.dist-info/WHEEL
infervcpy-1.6.dist-info/top_level.txt
infervcpy-1.6.dist-info/RECORD
