Metadata-Version: 2.2
Name: infervcpy
Version: 1.6
Summary: Python wrapper for fast inference with rvc
Home-page: https://github.com/thatneos/python-rvc-inference.git
Author: Neofr
License: MIT
Requires-Python: >=3.10
License-File: LICENSE
Requires-Dist: torch
Requires-Dist: torchaudio
Requires-Dist: gradio==4.40.0
Requires-Dist: praat-parselmouth>=0.4.3
Requires-Dist: pyworld==0.3.2
Requires-Dist: faiss-cpu==1.7.3
Requires-Dist: torchcrepe==0.0.20
Requires-Dist: ffmpeg-python>=0.2.0
Requires-Dist: fairseq==0.12.2
Requires-Dist: typeguard==4.2.0
Requires-Dist: soundfile
Requires-Dist: yt-dlp
Requires-Dist: audio-separator[gpu]
Requires-Dist: librosa
Requires-Dist: numpy
Provides-Extra: all
Requires-Dist: scipy; extra == "all"
Requires-Dist: numba==0.56.4; extra == "all"
Requires-Dist: edge-tts; extra == "all"
Dynamic: author
Dynamic: description
Dynamic: description-content-type
Dynamic: home-page
Dynamic: license
Dynamic: provides-extra
Dynamic: requires-dist
Dynamic: requires-python
Dynamic: summary
